foliant/config/include.py
foliantcontrib.yaml_include-1.0.1.dist-info/LICENSE
foliantcontrib.yaml_include-1.0.1.dist-info/METADATA
foliantcontrib.yaml_include-1.0.1.dist-info/WHEEL
foliantcontrib.yaml_include-1.0.1.dist-info/top_level.txt
foliantcontrib.yaml_include-1.0.1.dist-info/RECORD
