Metadata-Version: 2.1
Name: foliantcontrib.yaml-include
Version: 1.0.1
Summary: Extension for Foliant documentation tool to include YAML-files in config and xml-tag parameters.
Home-page: https://github.com/foliant-docs/foliantcontrib.yaml_include
Author: Daniil Minukhin
Author-email: ddddsa@gmail.com
License: MIT
Platform: any
Classifier: Development Status :: 5 - Production/Stable
Classifier: Environment :: Console
Classifier: Intended Audience :: Developers
Classifier: License :: OSI Approved :: MIT License
Classifier: Operating System :: OS Independent
Classifier: Programming Language :: Python
Classifier: Topic :: Documentation
Classifier: Topic :: Utilities
Requires-Dist: foliant (>=1.0.4)
